{
  "java" : "соответствует",
  "c++" : "соответствует",
  "python" : "лучше ожидаемого",
  "javascript" : "требует улучшения",
  "sql" : "требует улучшения",
  "docker" : "соответствует",
  "c#" : "соответствует",
  "php" : "соответствует",
  "spring" : "требует улучшения",
  "machine_learning" : "соответствует",
  "react" : "соответствует",
  "typescript" : "требует улучшения",
  "kubernetes" : "соответствует",
  "terraform" : "соответствует",
  "linux" : "требует улучшения",
  "hibernate" : "соответствует",
  "spark" : "соответствует",
  "pandas" : "соответствует",
  "kafka" : "требует улучшения",
  "aws" : "требует улучшения"
}